xarray_regressions/__init__.py
xarray_regressions/fixture.py
xarray_regressions/plugin.py
xarray_regressions-0.0.3.dist-info/METADATA
xarray_regressions-0.0.3.dist-info/WHEEL
xarray_regressions-0.0.3.dist-info/entry_points.txt
xarray_regressions-0.0.3.dist-info/licenses/LICENSE
xarray_regressions-0.0.3.dist-info/RECORD
