Metadata-Version: 2.4
Name: xarray-regressions
Version: 0.0.3
Summary: pytest-regressions plugin for xarray
Author-email: Aaron Zuspan <aa.zuspan@gmail.com>
License-File: LICENSE
Classifier: Development Status :: 4 - Beta
Classifier: Framework :: Pytest
Classifier: Intended Audience :: Developers
Classifier: License :: OSI Approved :: MIT License
Classifier: Natural Language :: English
Classifier: Programming Language :: Python :: 3
Classifier: Topic :: Software Development :: Testing
Requires-Python: >=3.9
Requires-Dist: netcdf4
Requires-Dist: pytest
Requires-Dist: pytest-regressions
Requires-Dist: xarray
